[
  {
    "x": 0,
    "y": 0,
    "width": 38,
    "height": 21,
    "pivotX": -19,
    "pivotY": -49
  },
  {
    "x": 38,
    "y": 0,
    "width": 38,
    "height": 21,
    "pivotX": -19,
    "pivotY": -50
  },
  {
    "x": 76,
    "y": 0,
    "width": 38,
    "height": 21,
    "pivotX": -19,
    "pivotY": -51
  },
  {
    "x": 114,
    "y": 0,
    "width": 38,
    "height": 21,
    "pivotX": -19,
    "pivotY": -50
  },
  {
    "x": 152,
    "y": 0,
    "width": 38,
    "height": 21,
    "pivotX": -19,
    "pivotY": -49
  },
  {
    "x": 190,
    "y": 0,
    "width": 38,
    "height": 21,
    "pivotX": -19,
    "pivotY": -50
  },
  {
    "x": 228,
    "y": 0,
    "width": 38,
    "height": 21,
    "pivotX": -19,
    "pivotY": -51
  },
  {
    "x": 266,
    "y": 0,
    "width": 38,
    "height": 21,
    "pivotX": -19,
    "pivotY": -50
  }
]