[
  {
    "x": 0,
    "y": 0,
    "width": 7,
    "height": 14,
    "pivotX": -14,
    "pivotY": -32
  },
  {
    "x": 7,
    "y": 0,
    "width": 5,
    "height": 28,
    "pivotX": -14,
    "pivotY": -44
  },
  {
    "x": 12,
    "y": 0,
    "width": 7,
    "height": 43,
    "pivotX": -14,
    "pivotY": -55
  },
  {
    "x": 19,
    "y": 0,
    "width": 10,
    "height": 49,
    "pivotX": -15,
    "pivotY": -61
  },
  {
    "x": 29,
    "y": 0,
    "width": 10,
    "height": 51,
    "pivotX": -15,
    "pivotY": -63
  },
  {
    "x": 39,
    "y": 0,
    "width": 10,
    "height": 49,
    "pivotX": -15,
    "pivotY": -61
  },
  {
    "x": 49,
    "y": 0,
    "width": 7,
    "height": 43,
    "pivotX": -14,
    "pivotY": -55
  },
  {
    "x": 56,
    "y": 0,
    "width": 5,
    "height": 29,
    "pivotX": -14,
    "pivotY": -44
  }
]