[
  {
    "x": 0,
    "y": 0,
    "width": 16,
    "height": 29,
    "pivotX": -13,
    "pivotY": -69
  },
  {
    "x": 16,
    "y": 0,
    "width": 16,
    "height": 28,
    "pivotX": -13,
    "pivotY": -69
  },
  {
    "x": 32,
    "y": 0,
    "width": 16,
    "height": 35,
    "pivotX": -13,
    "pivotY": -70
  },
  {
    "x": 48,
    "y": 0,
    "width": 16,
    "height": 28,
    "pivotX": -13,
    "pivotY": -69
  },
  {
    "x": 64,
    "y": 0,
    "width": 16,
    "height": 29,
    "pivotX": -13,
    "pivotY": -69
  },
  {
    "x": 80,
    "y": 0,
    "width": 16,
    "height": 28,
    "pivotX": -13,
    "pivotY": -69
  },
  {
    "x": 96,
    "y": 0,
    "width": 16,
    "height": 28,
    "pivotX": -13,
    "pivotY": -70
  },
  {
    "x": 112,
    "y": 0,
    "width": 16,
    "height": 29,
    "pivotX": -13,
    "pivotY": -70
  }
]