[
  {
    "x": 0,
    "y": 0,
    "width": 5,
    "height": 10,
    "pivotX": -9,
    "pivotY": -28
  },
  {
    "x": 5,
    "y": 0,
    "width": 5,
    "height": 10,
    "pivotX": -10,
    "pivotY": -27
  },
  {
    "x": 10,
    "y": 0,
    "width": 4,
    "height": 14,
    "pivotX": -10,
    "pivotY": -29
  },
  {
    "x": 14,
    "y": 0,
    "width": 5,
    "height": 17,
    "pivotX": -11,
    "pivotY": -31
  },
  {
    "x": 19,
    "y": 0,
    "width": 5,
    "height": 18,
    "pivotX": -11,
    "pivotY": -32
  },
  {
    "x": 24,
    "y": 0,
    "width": 5,
    "height": 18,
    "pivotX": -11,
    "pivotY": -32
  },
  {
    "x": 29,
    "y": 0,
    "width": 4,
    "height": 14,
    "pivotX": -10,
    "pivotY": -29
  },
  {
    "x": 33,
    "y": 0,
    "width": 5,
    "height": 11,
    "pivotX": -10,
    "pivotY": -27
  }
]