[
  {
    "x": 0,
    "y": 0,
    "width": 14,
    "height": 23,
    "pivotX": -15,
    "pivotY": -64
  },
  {
    "x": 14,
    "y": 0,
    "width": 11,
    "height": 33,
    "pivotX": -15,
    "pivotY": -79
  },
  {
    "x": 25,
    "y": 0,
    "width": 29,
    "height": 54,
    "pivotX": -21,
    "pivotY": -77
  },
  {
    "x": 54,
    "y": 0,
    "width": 33,
    "height": 39,
    "pivotX": -18,
    "pivotY": -63
  },
  {
    "x": 87,
    "y": 0,
    "width": 31,
    "height": 28,
    "pivotX": -14,
    "pivotY": -52
  },
  {
    "x": 118,
    "y": 0,
    "width": 33,
    "height": 38,
    "pivotX": -18,
    "pivotY": -61
  },
  {
    "x": 151,
    "y": 0,
    "width": 30,
    "height": 54,
    "pivotX": -21,
    "pivotY": -78
  },
  {
    "x": 181,
    "y": 0,
    "width": 10,
    "height": 34,
    "pivotX": -15,
    "pivotY": -82
  }
]