[
  {
    "x": 0,
    "y": 0,
    "width": 56,
    "height": 25,
    "pivotX": -48,
    "pivotY": -51
  },
  {
    "x": 56,
    "y": 0,
    "width": 57,
    "height": 23,
    "pivotX": -49,
    "pivotY": -49
  },
  {
    "x": 113,
    "y": 0,
    "width": 59,
    "height": 21,
    "pivotX": -51,
    "pivotY": -46
  },
  {
    "x": 172,
    "y": 0,
    "width": 61,
    "height": 19,
    "pivotX": -53,
    "pivotY": -44
  },
  {
    "x": 233,
    "y": 0,
    "width": 61,
    "height": 19,
    "pivotX": -53,
    "pivotY": -44
  },
  {
    "x": 294,
    "y": 0,
    "width": 61,
    "height": 19,
    "pivotX": -53,
    "pivotY": -44
  },
  {
    "x": 355,
    "y": 0,
    "width": 59,
    "height": 21,
    "pivotX": -51,
    "pivotY": -46
  },
  {
    "x": 414,
    "y": 0,
    "width": 57,
    "height": 23,
    "pivotX": -49,
    "pivotY": -49
  }
]