[
  {
    "x": 0,
    "y": 0,
    "width": 16,
    "height": 23,
    "pivotX": -16,
    "pivotY": -64
  },
  {
    "x": 16,
    "y": 0,
    "width": 11,
    "height": 39,
    "pivotX": -15,
    "pivotY": -83
  },
  {
    "x": 27,
    "y": 0,
    "width": 31,
    "height": 58,
    "pivotX": -23,
    "pivotY": -81
  },
  {
    "x": 58,
    "y": 0,
    "width": 35,
    "height": 40,
    "pivotX": -20,
    "pivotY": -65
  },
  {
    "x": 93,
    "y": 0,
    "width": 34,
    "height": 31,
    "pivotX": -17,
    "pivotY": -53
  },
  {
    "x": 127,
    "y": 0,
    "width": 35,
    "height": 41,
    "pivotX": -20,
    "pivotY": -64
  },
  {
    "x": 162,
    "y": 0,
    "width": 31,
    "height": 57,
    "pivotX": -23,
    "pivotY": -81
  },
  {
    "x": 193,
    "y": 0,
    "width": 11,
    "height": 38,
    "pivotX": -15,
    "pivotY": -85
  }
]