[
  {
    "x": 0,
    "y": 0,
    "width": 8,
    "height": 11,
    "pivotX": -4,
    "pivotY": -57
  },
  {
    "x": 8,
    "y": 0,
    "width": 7,
    "height": 11,
    "pivotX": -4,
    "pivotY": -57
  },
  {
    "x": 15,
    "y": 0,
    "width": 8,
    "height": 11,
    "pivotX": -4,
    "pivotY": -58
  },
  {
    "x": 23,
    "y": 0,
    "width": 8,
    "height": 9,
    "pivotX": -1,
    "pivotY": -57
  },
  {
    "x": 31,
    "y": 0,
    "width": 7,
    "height": 7,
    "pivotX": -4,
    "pivotY": -49
  },
  {
    "x": 38,
    "y": 0,
    "width": 7,
    "height": 9,
    "pivotX": -2,
    "pivotY": -53
  },
  {
    "x": 45,
    "y": 0,
    "width": 7,
    "height": 10,
    "pivotX": -1,
    "pivotY": -58
  },
  {
    "x": 52,
    "y": 0,
    "width": 8,
    "height": 12,
    "pivotX": -4,
    "pivotY": -57
  },
  {
    "x": 0,
    "y": 12,
    "width": 7,
    "height": 11,
    "pivotX": -4,
    "pivotY": -57
  },
  {
    "x": 7,
    "y": 12,
    "width": 8,
    "height": 11,
    "pivotX": -4,
    "pivotY": -57
  },
  {
    "x": 15,
    "y": 12,
    "width": 7,
    "height": 10,
    "pivotX": -1,
    "pivotY": -57
  },
  {
    "x": 22,
    "y": 12,
    "width": 8,
    "height": 9,
    "pivotX": 10,
    "pivotY": -54
  },
  {
    "x": 30,
    "y": 12,
    "width": 7,
    "height": 8,
    "pivotX": 11,
    "pivotY": -47
  },
  {
    "x": 37,
    "y": 12,
    "width": 8,
    "height": 9,
    "pivotX": 10,
    "pivotY": -51
  },
  {
    "x": 45,
    "y": 12,
    "width": 8,
    "height": 10,
    "pivotX": 5,
    "pivotY": -56
  },
  {
    "x": 53,
    "y": 12,
    "width": 7,
    "height": 11,
    "pivotX": -4,
    "pivotY": -57
  },
  {
    "x": 0,
    "y": 23,
    "width": 8,
    "height": 9,
    "pivotX": -5,
    "pivotY": -57
  },
  {
    "x": 8,
    "y": 23,
    "width": 9,
    "height": 9,
    "pivotX": -4,
    "pivotY": -56
  },
  {
    "x": 17,
    "y": 23,
    "width": 8,
    "height": 7,
    "pivotX": 1,
    "pivotY": -54
  },
  {
    "x": 25,
    "y": 23,
    "width": 10,
    "height": 8,
    "pivotX": 17,
    "pivotY": -44
  },
  {
    "x": 35,
    "y": 23,
    "width": 9,
    "height": 7,
    "pivotX": 25,
    "pivotY": -34
  },
  {
    "x": 44,
    "y": 23,
    "width": 9,
    "height": 8,
    "pivotX": 21,
    "pivotY": -39
  },
  {
    "x": 53,
    "y": 23,
    "width": 9,
    "height": 8,
    "pivotX": 9,
    "pivotY": -49
  },
  {
    "x": 62,
    "y": 23,
    "width": 8,
    "height": 9,
    "pivotX": -5,
    "pivotY": -56
  },
  {
    "x": 0,
    "y": 32,
    "width": 8,
    "height": 7,
    "pivotX": -5,
    "pivotY": -57
  },
  {
    "x": 8,
    "y": 32,
    "width": 8,
    "height": 7,
    "pivotX": -4,
    "pivotY": -56
  },
  {
    "x": 16,
    "y": 32,
    "width": 8,
    "height": 7,
    "pivotX": -2,
    "pivotY": -52
  },
  {
    "x": 24,
    "y": 32,
    "width": 9,
    "height": 7,
    "pivotX": 3,
    "pivotY": -35
  },
  {
    "x": 33,
    "y": 32,
    "width": 8,
    "height": 7,
    "pivotX": 10,
    "pivotY": -21
  },
  {
    "x": 41,
    "y": 32,
    "width": 8,
    "height": 7,
    "pivotX": 7,
    "pivotY": -28
  },
  {
    "x": 49,
    "y": 32,
    "width": 8,
    "height": 7,
    "pivotX": 0,
    "pivotY": -44
  },
  {
    "x": 57,
    "y": 32,
    "width": 8,
    "height": 8,
    "pivotX": -5,
    "pivotY": -57
  },
  {
    "x": 0,
    "y": 40,
    "width": 8,
    "height": 7,
    "pivotX": -5,
    "pivotY": -58
  },
  {
    "x": 8,
    "y": 40,
    "width": 7,
    "height": 7,
    "pivotX": -4,
    "pivotY": -56
  },
  {
    "x": 15,
    "y": 40,
    "width": 8,
    "height": 7,
    "pivotX": -5,
    "pivotY": -52
  },
  {
    "x": 23,
    "y": 40,
    "width": 7,
    "height": 8,
    "pivotX": -8,
    "pivotY": -35
  },
  {
    "x": 30,
    "y": 40,
    "width": 7,
    "height": 7,
    "pivotX": -4,
    "pivotY": -19
  },
  {
    "x": 37,
    "y": 40,
    "width": 7,
    "height": 7,
    "pivotX": -6,
    "pivotY": -27
  },
  {
    "x": 44,
    "y": 40,
    "width": 7,
    "height": 7,
    "pivotX": -7,
    "pivotY": -44
  },
  {
    "x": 51,
    "y": 40,
    "width": 8,
    "height": 7,
    "pivotX": -5,
    "pivotY": -57
  },
  {
    "x": 0,
    "y": 48,
    "width": 7,
    "height": 9,
    "pivotX": -4,
    "pivotY": -58
  },
  {
    "x": 7,
    "y": 48,
    "width": 8,
    "height": 8,
    "pivotX": -5,
    "pivotY": -56
  },
  {
    "x": 15,
    "y": 48,
    "width": 8,
    "height": 7,
    "pivotX": -8,
    "pivotY": -53
  },
  {
    "x": 23,
    "y": 48,
    "width": 8,
    "height": 7,
    "pivotX": -19,
    "pivotY": -37
  },
  {
    "x": 31,
    "y": 48,
    "width": 8,
    "height": 8,
    "pivotX": -20,
    "pivotY": -22
  },
  {
    "x": 39,
    "y": 48,
    "width": 8,
    "height": 7,
    "pivotX": -19,
    "pivotY": -29
  },
  {
    "x": 47,
    "y": 48,
    "width": 7,
    "height": 7,
    "pivotX": -14,
    "pivotY": -46
  },
  {
    "x": 54,
    "y": 48,
    "width": 7,
    "height": 8,
    "pivotX": -4,
    "pivotY": -57
  },
  {
    "x": 0,
    "y": 57,
    "width": 8,
    "height": 10,
    "pivotX": -4,
    "pivotY": -58
  },
  {
    "x": 8,
    "y": 57,
    "width": 9,
    "height": 9,
    "pivotX": -6,
    "pivotY": -56
  },
  {
    "x": 17,
    "y": 57,
    "width": 10,
    "height": 8,
    "pivotX": -10,
    "pivotY": -55
  },
  {
    "x": 27,
    "y": 57,
    "width": 10,
    "height": 7,
    "pivotX": -28,
    "pivotY": -47
  },
  {
    "x": 37,
    "y": 57,
    "width": 9,
    "height": 7,
    "pivotX": -35,
    "pivotY": -34
  },
  {
    "x": 46,
    "y": 57,
    "width": 9,
    "height": 8,
    "pivotX": -31,
    "pivotY": -41
  },
  {
    "x": 55,
    "y": 57,
    "width": 9,
    "height": 8,
    "pivotX": -19,
    "pivotY": -52
  },
  {
    "x": 64,
    "y": 57,
    "width": 8,
    "height": 10,
    "pivotX": -4,
    "pivotY": -57
  },
  {
    "x": 0,
    "y": 67,
    "width": 8,
    "height": 12,
    "pivotX": -4,
    "pivotY": -58
  },
  {
    "x": 8,
    "y": 67,
    "width": 8,
    "height": 11,
    "pivotX": -5,
    "pivotY": -57
  },
  {
    "x": 16,
    "y": 67,
    "width": 9,
    "height": 10,
    "pivotX": -7,
    "pivotY": -57
  },
  {
    "x": 25,
    "y": 67,
    "width": 9,
    "height": 9,
    "pivotX": -13,
    "pivotY": -56
  },
  {
    "x": 34,
    "y": 67,
    "width": 8,
    "height": 5,
    "pivotX": -20,
    "pivotY": -47
  },
  {
    "x": 42,
    "y": 67,
    "width": 8,
    "height": 7,
    "pivotX": -16,
    "pivotY": -51
  },
  {
    "x": 50,
    "y": 67,
    "width": 8,
    "height": 10,
    "pivotX": -9,
    "pivotY": -58
  },
  {
    "x": 58,
    "y": 67,
    "width": 8,
    "height": 11,
    "pivotX": -4,
    "pivotY": -57
  }
]