[
  {
    "x": 0,
    "y": 0,
    "width": 14,
    "height": 48,
    "pivotX": 2,
    "pivotY": -49
  },
  {
    "x": 14,
    "y": 0,
    "width": 13,
    "height": 46,
    "pivotX": 3,
    "pivotY": -48
  },
  {
    "x": 27,
    "y": 0,
    "width": 11,
    "height": 39,
    "pivotX": 5,
    "pivotY": -42
  },
  {
    "x": 38,
    "y": 0,
    "width": 11,
    "height": 37,
    "pivotX": 5,
    "pivotY": -41
  },
  {
    "x": 49,
    "y": 0,
    "width": 11,
    "height": 37,
    "pivotX": 5,
    "pivotY": -41
  },
  {
    "x": 60,
    "y": 0,
    "width": 11,
    "height": 37,
    "pivotX": 5,
    "pivotY": -41
  },
  {
    "x": 71,
    "y": 0,
    "width": 11,
    "height": 39,
    "pivotX": 5,
    "pivotY": -42
  },
  {
    "x": 82,
    "y": 0,
    "width": 13,
    "height": 46,
    "pivotX": 3,
    "pivotY": -48
  }
]