[
  {
    "x": 0,
    "y": 0,
    "width": 50,
    "height": 21,
    "pivotX": -35,
    "pivotY": -42
  },
  {
    "x": 50,
    "y": 0,
    "width": 50,
    "height": 22,
    "pivotX": -35,
    "pivotY": -43
  },
  {
    "x": 100,
    "y": 0,
    "width": 49,
    "height": 22,
    "pivotX": -34,
    "pivotY": -43
  },
  {
    "x": 149,
    "y": 0,
    "width": 49,
    "height": 22,
    "pivotX": -34,
    "pivotY": -43
  },
  {
    "x": 198,
    "y": 0,
    "width": 49,
    "height": 23,
    "pivotX": -34,
    "pivotY": -44
  },
  {
    "x": 247,
    "y": 0,
    "width": 49,
    "height": 22,
    "pivotX": -34,
    "pivotY": -43
  },
  {
    "x": 296,
    "y": 0,
    "width": 49,
    "height": 22,
    "pivotX": -34,
    "pivotY": -43
  },
  {
    "x": 345,
    "y": 0,
    "width": 50,
    "height": 22,
    "pivotX": -35,
    "pivotY": -43
  }
]