[
  {
    "x": 0,
    "y": 0,
    "width": 12,
    "height": 33,
    "pivotX": -12,
    "pivotY": -34
  },
  {
    "x": 12,
    "y": 0,
    "width": 11,
    "height": 15,
    "pivotX": -15,
    "pivotY": -29
  },
  {
    "x": 23,
    "y": 0,
    "width": 8,
    "height": 14,
    "pivotX": -16,
    "pivotY": -33
  },
  {
    "x": 31,
    "y": 0,
    "width": 19,
    "height": 27,
    "pivotX": -20,
    "pivotY": -48
  },
  {
    "x": 50,
    "y": 0,
    "width": 24,
    "height": 31,
    "pivotX": -20,
    "pivotY": -51
  },
  {
    "x": 74,
    "y": 0,
    "width": 19,
    "height": 27,
    "pivotX": -20,
    "pivotY": -46
  },
  {
    "x": 93,
    "y": 0,
    "width": 9,
    "height": 14,
    "pivotX": -17,
    "pivotY": -33
  },
  {
    "x": 102,
    "y": 0,
    "width": 11,
    "height": 16,
    "pivotX": -15,
    "pivotY": -32
  }
]