[
  {
    "x": 0,
    "y": 0,
    "width": 24,
    "height": 35,
    "pivotX": -1,
    "pivotY": -64
  },
  {
    "x": 24,
    "y": 0,
    "width": 31,
    "height": 21,
    "pivotX": -14,
    "pivotY": -62
  },
  {
    "x": 55,
    "y": 0,
    "width": 27,
    "height": 22,
    "pivotX": -11,
    "pivotY": -61
  },
  {
    "x": 82,
    "y": 0,
    "width": 22,
    "height": 29,
    "pivotX": 24,
    "pivotY": -70
  },
  {
    "x": 104,
    "y": 0,
    "width": 14,
    "height": 24,
    "pivotX": 13,
    "pivotY": -44
  },
  {
    "x": 118,
    "y": 0,
    "width": 17,
    "height": 27,
    "pivotX": 12,
    "pivotY": -49
  },
  {
    "x": 135,
    "y": 0,
    "width": 25,
    "height": 35,
    "pivotX": 14,
    "pivotY": -61
  },
  {
    "x": 160,
    "y": 0,
    "width": 24,
    "height": 35,
    "pivotX": -1,
    "pivotY": -63
  }
]