[
  {
    "x": 0,
    "y": 0,
    "width": 18,
    "height": 30,
    "pivotX": -9,
    "pivotY": -47
  },
  {
    "x": 18,
    "y": 0,
    "width": 17,
    "height": 30,
    "pivotX": -8,
    "pivotY": -46
  },
  {
    "x": 35,
    "y": 0,
    "width": 17,
    "height": 28,
    "pivotX": -8,
    "pivotY": -42
  },
  {
    "x": 52,
    "y": 0,
    "width": 17,
    "height": 28,
    "pivotX": -8,
    "pivotY": -39
  },
  {
    "x": 69,
    "y": 0,
    "width": 19,
    "height": 36,
    "pivotX": -10,
    "pivotY": -44
  },
  {
    "x": 88,
    "y": 0,
    "width": 22,
    "height": 29,
    "pivotX": -12,
    "pivotY": -34
  },
  {
    "x": 110,
    "y": 0,
    "width": 21,
    "height": 30,
    "pivotX": -12,
    "pivotY": -34
  },
  {
    "x": 131,
    "y": 0,
    "width": 20,
    "height": 33,
    "pivotX": -12,
    "pivotY": -37
  },
  {
    "x": 151,
    "y": 0,
    "width": 21,
    "height": 30,
    "pivotX": -12,
    "pivotY": -34
  },
  {
    "x": 172,
    "y": 0,
    "width": 23,
    "height": 29,
    "pivotX": -12,
    "pivotY": -34
  },
  {
    "x": 195,
    "y": 0,
    "width": 28,
    "height": 29,
    "pivotX": -12,
    "pivotY": -34
  },
  {
    "x": 223,
    "y": 0,
    "width": 35,
    "height": 29,
    "pivotX": -12,
    "pivotY": -34
  },
  {
    "x": 258,
    "y": 0,
    "width": 35,
    "height": 28,
    "pivotX": -12,
    "pivotY": -33
  },
  {
    "x": 293,
    "y": 0,
    "width": 29,
    "height": 35,
    "pivotX": -10,
    "pivotY": -45
  },
  {
    "x": 322,
    "y": 0,
    "width": 19,
    "height": 28,
    "pivotX": -8,
    "pivotY": -42
  },
  {
    "x": 341,
    "y": 0,
    "width": 18,
    "height": 30,
    "pivotX": -9,
    "pivotY": -47
  },
  {
    "x": 0,
    "y": 36,
    "width": 17,
    "height": 32,
    "pivotX": -8,
    "pivotY": -48
  },
  {
    "x": 17,
    "y": 36,
    "width": 17,
    "height": 31,
    "pivotX": -8,
    "pivotY": -46
  },
  {
    "x": 34,
    "y": 36,
    "width": 17,
    "height": 32,
    "pivotX": -9,
    "pivotY": -45
  },
  {
    "x": 51,
    "y": 36,
    "width": 17,
    "height": 28,
    "pivotX": -10,
    "pivotY": -39
  },
  {
    "x": 68,
    "y": 36,
    "width": 17,
    "height": 36,
    "pivotX": -10,
    "pivotY": -43
  },
  {
    "x": 85,
    "y": 36,
    "width": 21,
    "height": 30,
    "pivotX": -12,
    "pivotY": -34
  },
  {
    "x": 106,
    "y": 36,
    "width": 26,
    "height": 30,
    "pivotX": -12,
    "pivotY": -34
  },
  {
    "x": 132,
    "y": 36,
    "width": 23,
    "height": 32,
    "pivotX": -12,
    "pivotY": -36
  },
  {
    "x": 155,
    "y": 36,
    "width": 21,
    "height": 30,
    "pivotX": -12,
    "pivotY": -34
  },
  {
    "x": 176,
    "y": 36,
    "width": 20,
    "height": 30,
    "pivotX": -12,
    "pivotY": -34
  },
  {
    "x": 196,
    "y": 36,
    "width": 25,
    "height": 30,
    "pivotX": -12,
    "pivotY": -34
  },
  {
    "x": 221,
    "y": 36,
    "width": 32,
    "height": 30,
    "pivotX": -12,
    "pivotY": -34
  },
  {
    "x": 253,
    "y": 36,
    "width": 32,
    "height": 30,
    "pivotX": -12,
    "pivotY": -34
  },
  {
    "x": 285,
    "y": 36,
    "width": 26,
    "height": 36,
    "pivotX": -11,
    "pivotY": -45
  },
  {
    "x": 311,
    "y": 36,
    "width": 17,
    "height": 31,
    "pivotX": -9,
    "pivotY": -45
  },
  {
    "x": 328,
    "y": 36,
    "width": 17,
    "height": 32,
    "pivotX": -8,
    "pivotY": -48
  },
  {
    "x": 0,
    "y": 72,
    "width": 11,
    "height": 33,
    "pivotX": -6,
    "pivotY": -49
  },
  {
    "x": 11,
    "y": 72,
    "width": 13,
    "height": 33,
    "pivotX": -7,
    "pivotY": -47
  },
  {
    "x": 24,
    "y": 72,
    "width": 15,
    "height": 32,
    "pivotX": -9,
    "pivotY": -44
  },
  {
    "x": 39,
    "y": 72,
    "width": 16,
    "height": 33,
    "pivotX": -11,
    "pivotY": -43
  },
  {
    "x": 55,
    "y": 72,
    "width": 17,
    "height": 37,
    "pivotX": -12,
    "pivotY": -44
  },
  {
    "x": 72,
    "y": 72,
    "width": 17,
    "height": 40,
    "pivotX": -13,
    "pivotY": -44
  },
  {
    "x": 89,
    "y": 72,
    "width": 26,
    "height": 40,
    "pivotX": -13,
    "pivotY": -44
  },
  {
    "x": 115,
    "y": 72,
    "width": 24,
    "height": 40,
    "pivotX": -13,
    "pivotY": -44
  },
  {
    "x": 139,
    "y": 72,
    "width": 21,
    "height": 40,
    "pivotX": -13,
    "pivotY": -44
  },
  {
    "x": 160,
    "y": 72,
    "width": 17,
    "height": 40,
    "pivotX": -13,
    "pivotY": -44
  },
  {
    "x": 177,
    "y": 72,
    "width": 17,
    "height": 40,
    "pivotX": -13,
    "pivotY": -44
  },
  {
    "x": 194,
    "y": 72,
    "width": 17,
    "height": 40,
    "pivotX": -13,
    "pivotY": -44
  },
  {
    "x": 211,
    "y": 72,
    "width": 17,
    "height": 40,
    "pivotX": -13,
    "pivotY": -44
  },
  {
    "x": 228,
    "y": 72,
    "width": 16,
    "height": 36,
    "pivotX": -11,
    "pivotY": -44
  },
  {
    "x": 244,
    "y": 72,
    "width": 14,
    "height": 33,
    "pivotX": -8,
    "pivotY": -45
  },
  {
    "x": 258,
    "y": 72,
    "width": 11,
    "height": 33,
    "pivotX": -6,
    "pivotY": -49
  },
  {
    "x": 0,
    "y": 112,
    "width": 16,
    "height": 33,
    "pivotX": -8,
    "pivotY": -50
  },
  {
    "x": 16,
    "y": 112,
    "width": 17,
    "height": 32,
    "pivotX": -9,
    "pivotY": -47
  },
  {
    "x": 33,
    "y": 112,
    "width": 16,
    "height": 31,
    "pivotX": -9,
    "pivotY": -43
  },
  {
    "x": 49,
    "y": 112,
    "width": 17,
    "height": 32,
    "pivotX": -10,
    "pivotY": -42
  },
  {
    "x": 66,
    "y": 112,
    "width": 17,
    "height": 35,
    "pivotX": -10,
    "pivotY": -43
  },
  {
    "x": 83,
    "y": 112,
    "width": 19,
    "height": 37,
    "pivotX": -11,
    "pivotY": -43
  },
  {
    "x": 102,
    "y": 112,
    "width": 19,
    "height": 37,
    "pivotX": -11,
    "pivotY": -43
  },
  {
    "x": 121,
    "y": 112,
    "width": 19,
    "height": 37,
    "pivotX": -11,
    "pivotY": -43
  },
  {
    "x": 140,
    "y": 112,
    "width": 19,
    "height": 37,
    "pivotX": -11,
    "pivotY": -43
  },
  {
    "x": 159,
    "y": 112,
    "width": 21,
    "height": 37,
    "pivotX": -13,
    "pivotY": -43
  },
  {
    "x": 180,
    "y": 112,
    "width": 24,
    "height": 37,
    "pivotX": -16,
    "pivotY": -43
  },
  {
    "x": 204,
    "y": 112,
    "width": 29,
    "height": 37,
    "pivotX": -21,
    "pivotY": -43
  },
  {
    "x": 233,
    "y": 112,
    "width": 29,
    "height": 37,
    "pivotX": -21,
    "pivotY": -43
  },
  {
    "x": 262,
    "y": 112,
    "width": 27,
    "height": 34,
    "pivotX": -20,
    "pivotY": -43
  },
  {
    "x": 289,
    "y": 112,
    "width": 19,
    "height": 32,
    "pivotX": -12,
    "pivotY": -45
  },
  {
    "x": 308,
    "y": 112,
    "width": 16,
    "height": 33,
    "pivotX": -8,
    "pivotY": -50
  },
  {
    "x": 0,
    "y": 149,
    "width": 18,
    "height": 33,
    "pivotX": -10,
    "pivotY": -50
  },
  {
    "x": 18,
    "y": 149,
    "width": 17,
    "height": 32,
    "pivotX": -10,
    "pivotY": -47
  },
  {
    "x": 35,
    "y": 149,
    "width": 17,
    "height": 30,
    "pivotX": -10,
    "pivotY": -43
  },
  {
    "x": 52,
    "y": 149,
    "width": 17,
    "height": 31,
    "pivotX": -10,
    "pivotY": -42
  },
  {
    "x": 69,
    "y": 149,
    "width": 19,
    "height": 32,
    "pivotX": -10,
    "pivotY": -42
  },
  {
    "x": 88,
    "y": 149,
    "width": 22,
    "height": 34,
    "pivotX": -11,
    "pivotY": -42
  },
  {
    "x": 110,
    "y": 149,
    "width": 21,
    "height": 35,
    "pivotX": -10,
    "pivotY": -42
  },
  {
    "x": 131,
    "y": 149,
    "width": 20,
    "height": 35,
    "pivotX": -9,
    "pivotY": -42
  },
  {
    "x": 151,
    "y": 149,
    "width": 21,
    "height": 35,
    "pivotX": -10,
    "pivotY": -42
  },
  {
    "x": 172,
    "y": 149,
    "width": 23,
    "height": 35,
    "pivotX": -12,
    "pivotY": -42
  },
  {
    "x": 195,
    "y": 149,
    "width": 28,
    "height": 35,
    "pivotX": -17,
    "pivotY": -42
  },
  {
    "x": 223,
    "y": 149,
    "width": 35,
    "height": 34,
    "pivotX": -24,
    "pivotY": -42
  },
  {
    "x": 258,
    "y": 149,
    "width": 35,
    "height": 34,
    "pivotX": -24,
    "pivotY": -42
  },
  {
    "x": 293,
    "y": 149,
    "width": 29,
    "height": 32,
    "pivotX": -20,
    "pivotY": -42
  },
  {
    "x": 322,
    "y": 149,
    "width": 19,
    "height": 32,
    "pivotX": -12,
    "pivotY": -45
  },
  {
    "x": 341,
    "y": 149,
    "width": 18,
    "height": 33,
    "pivotX": -10,
    "pivotY": -50
  },
  {
    "x": 0,
    "y": 184,
    "width": 17,
    "height": 33,
    "pivotX": -10,
    "pivotY": -50
  },
  {
    "x": 17,
    "y": 184,
    "width": 16,
    "height": 32,
    "pivotX": -9,
    "pivotY": -47
  },
  {
    "x": 33,
    "y": 184,
    "width": 17,
    "height": 30,
    "pivotX": -9,
    "pivotY": -43
  },
  {
    "x": 50,
    "y": 184,
    "width": 17,
    "height": 31,
    "pivotX": -8,
    "pivotY": -42
  },
  {
    "x": 67,
    "y": 184,
    "width": 17,
    "height": 30,
    "pivotX": -8,
    "pivotY": -41
  },
  {
    "x": 84,
    "y": 184,
    "width": 21,
    "height": 26,
    "pivotX": -10,
    "pivotY": -35
  },
  {
    "x": 105,
    "y": 184,
    "width": 26,
    "height": 26,
    "pivotX": -15,
    "pivotY": -34
  },
  {
    "x": 131,
    "y": 184,
    "width": 23,
    "height": 26,
    "pivotX": -12,
    "pivotY": -34
  },
  {
    "x": 154,
    "y": 184,
    "width": 21,
    "height": 26,
    "pivotX": -10,
    "pivotY": -34
  },
  {
    "x": 175,
    "y": 184,
    "width": 20,
    "height": 27,
    "pivotX": -9,
    "pivotY": -35
  },
  {
    "x": 195,
    "y": 184,
    "width": 24,
    "height": 26,
    "pivotX": -13,
    "pivotY": -35
  },
  {
    "x": 219,
    "y": 184,
    "width": 32,
    "height": 26,
    "pivotX": -21,
    "pivotY": -35
  },
  {
    "x": 251,
    "y": 184,
    "width": 32,
    "height": 26,
    "pivotX": -21,
    "pivotY": -35
  },
  {
    "x": 283,
    "y": 184,
    "width": 26,
    "height": 31,
    "pivotX": -16,
    "pivotY": -42
  },
  {
    "x": 309,
    "y": 184,
    "width": 17,
    "height": 32,
    "pivotX": -9,
    "pivotY": -45
  },
  {
    "x": 326,
    "y": 184,
    "width": 17,
    "height": 33,
    "pivotX": -10,
    "pivotY": -50
  },
  {
    "x": 0,
    "y": 217,
    "width": 11,
    "height": 33,
    "pivotX": -6,
    "pivotY": -49
  },
  {
    "x": 11,
    "y": 217,
    "width": 13,
    "height": 33,
    "pivotX": -7,
    "pivotY": -47
  },
  {
    "x": 24,
    "y": 217,
    "width": 15,
    "height": 31,
    "pivotX": -7,
    "pivotY": -44
  },
  {
    "x": 39,
    "y": 217,
    "width": 17,
    "height": 31,
    "pivotX": -7,
    "pivotY": -43
  },
  {
    "x": 56,
    "y": 217,
    "width": 18,
    "height": 34,
    "pivotX": -7,
    "pivotY": -44
  },
  {
    "x": 74,
    "y": 217,
    "width": 17,
    "height": 36,
    "pivotX": -5,
    "pivotY": -44
  },
  {
    "x": 91,
    "y": 217,
    "width": 25,
    "height": 36,
    "pivotX": -13,
    "pivotY": -44
  },
  {
    "x": 116,
    "y": 217,
    "width": 24,
    "height": 36,
    "pivotX": -12,
    "pivotY": -44
  },
  {
    "x": 140,
    "y": 217,
    "width": 21,
    "height": 36,
    "pivotX": -9,
    "pivotY": -44
  },
  {
    "x": 161,
    "y": 217,
    "width": 17,
    "height": 36,
    "pivotX": -5,
    "pivotY": -44
  },
  {
    "x": 178,
    "y": 217,
    "width": 17,
    "height": 36,
    "pivotX": -5,
    "pivotY": -44
  },
  {
    "x": 195,
    "y": 217,
    "width": 17,
    "height": 36,
    "pivotX": -5,
    "pivotY": -44
  },
  {
    "x": 212,
    "y": 217,
    "width": 17,
    "height": 36,
    "pivotX": -5,
    "pivotY": -44
  },
  {
    "x": 229,
    "y": 217,
    "width": 16,
    "height": 33,
    "pivotX": -6,
    "pivotY": -44
  },
  {
    "x": 245,
    "y": 217,
    "width": 14,
    "height": 32,
    "pivotX": -7,
    "pivotY": -45
  },
  {
    "x": 259,
    "y": 217,
    "width": 11,
    "height": 34,
    "pivotX": -6,
    "pivotY": -50
  },
  {
    "x": 0,
    "y": 253,
    "width": 16,
    "height": 32,
    "pivotX": -9,
    "pivotY": -48
  },
  {
    "x": 16,
    "y": 253,
    "width": 17,
    "height": 31,
    "pivotX": -9,
    "pivotY": -46
  },
  {
    "x": 33,
    "y": 253,
    "width": 16,
    "height": 31,
    "pivotX": -8,
    "pivotY": -45
  },
  {
    "x": 49,
    "y": 253,
    "width": 17,
    "height": 34,
    "pivotX": -8,
    "pivotY": -45
  },
  {
    "x": 66,
    "y": 253,
    "width": 17,
    "height": 37,
    "pivotX": -8,
    "pivotY": -45
  },
  {
    "x": 83,
    "y": 253,
    "width": 19,
    "height": 39,
    "pivotX": -9,
    "pivotY": -45
  },
  {
    "x": 102,
    "y": 253,
    "width": 19,
    "height": 40,
    "pivotX": -9,
    "pivotY": -45
  },
  {
    "x": 121,
    "y": 253,
    "width": 19,
    "height": 40,
    "pivotX": -9,
    "pivotY": -45
  },
  {
    "x": 140,
    "y": 253,
    "width": 19,
    "height": 40,
    "pivotX": -9,
    "pivotY": -45
  },
  {
    "x": 159,
    "y": 253,
    "width": 21,
    "height": 40,
    "pivotX": -9,
    "pivotY": -45
  },
  {
    "x": 180,
    "y": 253,
    "width": 24,
    "height": 39,
    "pivotX": -9,
    "pivotY": -45
  },
  {
    "x": 204,
    "y": 253,
    "width": 30,
    "height": 39,
    "pivotX": -9,
    "pivotY": -45
  },
  {
    "x": 234,
    "y": 253,
    "width": 30,
    "height": 39,
    "pivotX": -9,
    "pivotY": -45
  },
  {
    "x": 264,
    "y": 253,
    "width": 26,
    "height": 35,
    "pivotX": -8,
    "pivotY": -45
  },
  {
    "x": 290,
    "y": 253,
    "width": 19,
    "height": 31,
    "pivotX": -8,
    "pivotY": -45
  },
  {
    "x": 309,
    "y": 253,
    "width": 16,
    "height": 32,
    "pivotX": -9,
    "pivotY": -48
  }
]