[
  {
    "x": 0,
    "y": 0,
    "width": 9,
    "height": 12,
    "pivotX": -5,
    "pivotY": -59
  },
  {
    "x": 9,
    "y": 0,
    "width": 8,
    "height": 10,
    "pivotX": -6,
    "pivotY": -50
  },
  {
    "x": 17,
    "y": 0,
    "width": 2,
    "height": 3,
    "pivotX": -6,
    "pivotY": -32
  },
  {
    "x": 19,
    "y": 0,
    "width": 8,
    "height": 10,
    "pivotX": -6,
    "pivotY": -50
  },
  {
    "x": 0,
    "y": 12,
    "width": 8,
    "height": 11,
    "pivotX": -3,
    "pivotY": -58
  },
  {
    "x": 8,
    "y": 12,
    "width": 9,
    "height": 11,
    "pivotX": 6,
    "pivotY": -49
  },
  {
    "x": 17,
    "y": 12,
    "width": 7,
    "height": 11,
    "pivotX": 8,
    "pivotY": -32
  },
  {
    "x": 24,
    "y": 12,
    "width": 9,
    "height": 11,
    "pivotX": 6,
    "pivotY": -49
  },
  {
    "x": 0,
    "y": 23,
    "width": 9,
    "height": 11,
    "pivotX": -1,
    "pivotY": -57
  },
  {
    "x": 9,
    "y": 23,
    "width": 11,
    "height": 12,
    "pivotX": 19,
    "pivotY": -39
  },
  {
    "x": 20,
    "y": 23,
    "width": 11,
    "height": 12,
    "pivotX": 18,
    "pivotY": -24
  },
  {
    "x": 31,
    "y": 23,
    "width": 11,
    "height": 12,
    "pivotX": 19,
    "pivotY": -39
  },
  {
    "x": 0,
    "y": 35,
    "width": 10,
    "height": 13,
    "pivotX": -4,
    "pivotY": -56
  },
  {
    "x": 10,
    "y": 35,
    "width": 9,
    "height": 11,
    "pivotX": 8,
    "pivotY": -28
  },
  {
    "x": 19,
    "y": 35,
    "width": 10,
    "height": 9,
    "pivotX": 7,
    "pivotY": -12
  },
  {
    "x": 29,
    "y": 35,
    "width": 9,
    "height": 11,
    "pivotX": 8,
    "pivotY": -28
  },
  {
    "x": 0,
    "y": 48,
    "width": 8,
    "height": 11,
    "pivotX": -4,
    "pivotY": -53
  },
  {
    "x": 8,
    "y": 48,
    "width": 8,
    "height": 9,
    "pivotX": -3,
    "pivotY": -24
  },
  {
    "x": 16,
    "y": 48,
    "width": 8,
    "height": 8,
    "pivotX": -3,
    "pivotY": -9
  },
  {
    "x": 24,
    "y": 48,
    "width": 8,
    "height": 9,
    "pivotX": -3,
    "pivotY": -24
  },
  {
    "x": 0,
    "y": 59,
    "width": 9,
    "height": 12,
    "pivotX": -6,
    "pivotY": -55
  },
  {
    "x": 9,
    "y": 59,
    "width": 9,
    "height": 11,
    "pivotX": -16,
    "pivotY": -27
  },
  {
    "x": 18,
    "y": 59,
    "width": 9,
    "height": 8,
    "pivotX": -16,
    "pivotY": -11
  },
  {
    "x": 27,
    "y": 59,
    "width": 9,
    "height": 11,
    "pivotX": -16,
    "pivotY": -27
  },
  {
    "x": 0,
    "y": 71,
    "width": 9,
    "height": 12,
    "pivotX": -9,
    "pivotY": -57
  },
  {
    "x": 9,
    "y": 71,
    "width": 11,
    "height": 12,
    "pivotX": -31,
    "pivotY": -38
  },
  {
    "x": 20,
    "y": 71,
    "width": 11,
    "height": 11,
    "pivotX": -30,
    "pivotY": -22
  },
  {
    "x": 31,
    "y": 71,
    "width": 11,
    "height": 12,
    "pivotX": -31,
    "pivotY": -38
  },
  {
    "x": 0,
    "y": 83,
    "width": 9,
    "height": 11,
    "pivotX": -7,
    "pivotY": -58
  },
  {
    "x": 9,
    "y": 83,
    "width": 9,
    "height": 11,
    "pivotX": -18,
    "pivotY": -48
  },
  {
    "x": 18,
    "y": 83,
    "width": 8,
    "height": 13,
    "pivotX": -18,
    "pivotY": -33
  },
  {
    "x": 26,
    "y": 83,
    "width": 9,
    "height": 11,
    "pivotX": -18,
    "pivotY": -48
  }
]