[
  {
    "x": 0,
    "y": 0,
    "width": 12,
    "height": 19,
    "pivotX": 10,
    "pivotY": -47
  },
  {
    "x": 12,
    "y": 0,
    "width": 12,
    "height": 19,
    "pivotX": 10,
    "pivotY": -48
  },
  {
    "x": 24,
    "y": 0,
    "width": 12,
    "height": 20,
    "pivotX": 10,
    "pivotY": -49
  },
  {
    "x": 36,
    "y": 0,
    "width": 12,
    "height": 19,
    "pivotX": 10,
    "pivotY": -48
  },
  {
    "x": 48,
    "y": 0,
    "width": 12,
    "height": 19,
    "pivotX": 10,
    "pivotY": -47
  },
  {
    "x": 60,
    "y": 0,
    "width": 12,
    "height": 19,
    "pivotX": 10,
    "pivotY": -48
  },
  {
    "x": 72,
    "y": 0,
    "width": 12,
    "height": 20,
    "pivotX": 10,
    "pivotY": -49
  },
  {
    "x": 84,
    "y": 0,
    "width": 12,
    "height": 19,
    "pivotX": 10,
    "pivotY": -48
  }
]