[
  {
    "x": 0,
    "y": 0,
    "width": 36,
    "height": 30,
    "pivotX": -13,
    "pivotY": -47
  },
  {
    "x": 36,
    "y": 0,
    "width": 34,
    "height": 33,
    "pivotX": -18,
    "pivotY": -41
  },
  {
    "x": 70,
    "y": 0,
    "width": 9,
    "height": 51,
    "pivotX": -5,
    "pivotY": -64
  },
  {
    "x": 79,
    "y": 0,
    "width": 10,
    "height": 51,
    "pivotX": -6,
    "pivotY": -64
  },
  {
    "x": 89,
    "y": 0,
    "width": 9,
    "height": 50,
    "pivotX": -5,
    "pivotY": -63
  },
  {
    "x": 98,
    "y": 0,
    "width": 8,
    "height": 51,
    "pivotX": -5,
    "pivotY": -63
  },
  {
    "x": 106,
    "y": 0,
    "width": 6,
    "height": 51,
    "pivotX": -5,
    "pivotY": -63
  },
  {
    "x": 112,
    "y": 0,
    "width": 8,
    "height": 37,
    "pivotX": -7,
    "pivotY": -57
  }
]