[
  {
    "x": 0,
    "y": 0,
    "width": 16,
    "height": 53,
    "pivotX": -19,
    "pivotY": -73
  },
  {
    "x": 16,
    "y": 0,
    "width": 16,
    "height": 53,
    "pivotX": -19,
    "pivotY": -74
  },
  {
    "x": 32,
    "y": 0,
    "width": 16,
    "height": 53,
    "pivotX": -19,
    "pivotY": -74
  },
  {
    "x": 48,
    "y": 0,
    "width": 16,
    "height": 52,
    "pivotX": -19,
    "pivotY": -73
  },
  {
    "x": 64,
    "y": 0,
    "width": 16,
    "height": 53,
    "pivotX": -19,
    "pivotY": -73
  },
  {
    "x": 80,
    "y": 0,
    "width": 16,
    "height": 53,
    "pivotX": -19,
    "pivotY": -74
  },
  {
    "x": 96,
    "y": 0,
    "width": 16,
    "height": 53,
    "pivotX": -19,
    "pivotY": -74
  },
  {
    "x": 112,
    "y": 0,
    "width": 16,
    "height": 53,
    "pivotX": -19,
    "pivotY": -74
  }
]