[
  {
    "x": 0,
    "y": 0,
    "width": 16,
    "height": 52,
    "pivotX": 10,
    "pivotY": -70
  },
  {
    "x": 16,
    "y": 0,
    "width": 32,
    "height": 44,
    "pivotX": 4,
    "pivotY": -59
  },
  {
    "x": 48,
    "y": 0,
    "width": 46,
    "height": 26,
    "pivotX": -4,
    "pivotY": -41
  },
  {
    "x": 94,
    "y": 0,
    "width": 53,
    "height": 12,
    "pivotX": -12,
    "pivotY": -29
  },
  {
    "x": 147,
    "y": 0,
    "width": 54,
    "height": 12,
    "pivotX": -15,
    "pivotY": -26
  },
  {
    "x": 201,
    "y": 0,
    "width": 53,
    "height": 12,
    "pivotX": -12,
    "pivotY": -27
  },
  {
    "x": 254,
    "y": 0,
    "width": 47,
    "height": 27,
    "pivotX": -4,
    "pivotY": -42
  },
  {
    "x": 301,
    "y": 0,
    "width": 32,
    "height": 45,
    "pivotX": 4,
    "pivotY": -62
  }
]