[
  {
    "x": 0,
    "y": 0,
    "width": 21,
    "height": 28,
    "pivotX": -11,
    "pivotY": -48
  },
  {
    "x": 21,
    "y": 0,
    "width": 22,
    "height": 27,
    "pivotX": -12,
    "pivotY": -48
  },
  {
    "x": 43,
    "y": 0,
    "width": 22,
    "height": 27,
    "pivotX": -12,
    "pivotY": -48
  },
  {
    "x": 65,
    "y": 0,
    "width": 21,
    "height": 28,
    "pivotX": -11,
    "pivotY": -48
  },
  {
    "x": 86,
    "y": 0,
    "width": 21,
    "height": 28,
    "pivotX": -11,
    "pivotY": -48
  },
  {
    "x": 107,
    "y": 0,
    "width": 21,
    "height": 27,
    "pivotX": -11,
    "pivotY": -48
  },
  {
    "x": 128,
    "y": 0,
    "width": 22,
    "height": 27,
    "pivotX": -12,
    "pivotY": -48
  },
  {
    "x": 150,
    "y": 0,
    "width": 21,
    "height": 27,
    "pivotX": -11,
    "pivotY": -47
  },
  {
    "x": 0,
    "y": 28,
    "width": 21,
    "height": 30,
    "pivotX": -12,
    "pivotY": -49
  },
  {
    "x": 21,
    "y": 28,
    "width": 20,
    "height": 30,
    "pivotX": -12,
    "pivotY": -50
  },
  {
    "x": 41,
    "y": 28,
    "width": 19,
    "height": 30,
    "pivotX": -11,
    "pivotY": -50
  },
  {
    "x": 60,
    "y": 28,
    "width": 18,
    "height": 31,
    "pivotX": -11,
    "pivotY": -50
  },
  {
    "x": 78,
    "y": 28,
    "width": 17,
    "height": 31,
    "pivotX": -10,
    "pivotY": -50
  },
  {
    "x": 95,
    "y": 28,
    "width": 18,
    "height": 30,
    "pivotX": -11,
    "pivotY": -50
  },
  {
    "x": 113,
    "y": 28,
    "width": 19,
    "height": 30,
    "pivotX": -11,
    "pivotY": -50
  },
  {
    "x": 132,
    "y": 28,
    "width": 20,
    "height": 30,
    "pivotX": -12,
    "pivotY": -49
  },
  {
    "x": 0,
    "y": 59,
    "width": 13,
    "height": 33,
    "pivotX": -8,
    "pivotY": -53
  },
  {
    "x": 13,
    "y": 59,
    "width": 13,
    "height": 33,
    "pivotX": -8,
    "pivotY": -53
  },
  {
    "x": 26,
    "y": 59,
    "width": 13,
    "height": 32,
    "pivotX": -8,
    "pivotY": -53
  },
  {
    "x": 39,
    "y": 59,
    "width": 13,
    "height": 32,
    "pivotX": -8,
    "pivotY": -51
  },
  {
    "x": 52,
    "y": 59,
    "width": 13,
    "height": 32,
    "pivotX": -8,
    "pivotY": -51
  },
  {
    "x": 65,
    "y": 59,
    "width": 13,
    "height": 32,
    "pivotX": -8,
    "pivotY": -52
  },
  {
    "x": 78,
    "y": 59,
    "width": 13,
    "height": 32,
    "pivotX": -8,
    "pivotY": -53
  },
  {
    "x": 91,
    "y": 59,
    "width": 13,
    "height": 34,
    "pivotX": -8,
    "pivotY": -53
  },
  {
    "x": 0,
    "y": 93,
    "width": 17,
    "height": 31,
    "pivotX": -10,
    "pivotY": -52
  },
  {
    "x": 17,
    "y": 93,
    "width": 19,
    "height": 31,
    "pivotX": -11,
    "pivotY": -52
  },
  {
    "x": 36,
    "y": 93,
    "width": 20,
    "height": 30,
    "pivotX": -12,
    "pivotY": -52
  },
  {
    "x": 56,
    "y": 93,
    "width": 20,
    "height": 30,
    "pivotX": -12,
    "pivotY": -51
  },
  {
    "x": 76,
    "y": 93,
    "width": 21,
    "height": 30,
    "pivotX": -12,
    "pivotY": -51
  },
  {
    "x": 97,
    "y": 93,
    "width": 21,
    "height": 29,
    "pivotX": -12,
    "pivotY": -51
  },
  {
    "x": 118,
    "y": 93,
    "width": 20,
    "height": 30,
    "pivotX": -12,
    "pivotY": -52
  },
  {
    "x": 138,
    "y": 93,
    "width": 19,
    "height": 31,
    "pivotX": -11,
    "pivotY": -52
  },
  {
    "x": 0,
    "y": 124,
    "width": 21,
    "height": 28,
    "pivotX": -11,
    "pivotY": -50
  },
  {
    "x": 21,
    "y": 124,
    "width": 22,
    "height": 27,
    "pivotX": -11,
    "pivotY": -50
  },
  {
    "x": 43,
    "y": 124,
    "width": 21,
    "height": 27,
    "pivotX": -11,
    "pivotY": -50
  },
  {
    "x": 64,
    "y": 124,
    "width": 21,
    "height": 28,
    "pivotX": -11,
    "pivotY": -50
  },
  {
    "x": 85,
    "y": 124,
    "width": 21,
    "height": 28,
    "pivotX": -11,
    "pivotY": -50
  },
  {
    "x": 106,
    "y": 124,
    "width": 21,
    "height": 28,
    "pivotX": -11,
    "pivotY": -51
  },
  {
    "x": 127,
    "y": 124,
    "width": 21,
    "height": 27,
    "pivotX": -11,
    "pivotY": -50
  },
  {
    "x": 148,
    "y": 124,
    "width": 21,
    "height": 28,
    "pivotX": -11,
    "pivotY": -50
  },
  {
    "x": 0,
    "y": 152,
    "width": 20,
    "height": 30,
    "pivotX": -9,
    "pivotY": -51
  },
  {
    "x": 20,
    "y": 152,
    "width": 20,
    "height": 31,
    "pivotX": -9,
    "pivotY": -52
  },
  {
    "x": 40,
    "y": 152,
    "width": 19,
    "height": 31,
    "pivotX": -9,
    "pivotY": -53
  },
  {
    "x": 59,
    "y": 152,
    "width": 18,
    "height": 31,
    "pivotX": -8,
    "pivotY": -52
  },
  {
    "x": 77,
    "y": 152,
    "width": 17,
    "height": 31,
    "pivotX": -8,
    "pivotY": -52
  },
  {
    "x": 94,
    "y": 152,
    "width": 18,
    "height": 31,
    "pivotX": -8,
    "pivotY": -53
  },
  {
    "x": 112,
    "y": 152,
    "width": 19,
    "height": 31,
    "pivotX": -9,
    "pivotY": -53
  },
  {
    "x": 131,
    "y": 152,
    "width": 20,
    "height": 30,
    "pivotX": -9,
    "pivotY": -51
  },
  {
    "x": 0,
    "y": 183,
    "width": 13,
    "height": 31,
    "pivotX": -6,
    "pivotY": -51
  },
  {
    "x": 13,
    "y": 183,
    "width": 13,
    "height": 32,
    "pivotX": -6,
    "pivotY": -52
  },
  {
    "x": 26,
    "y": 183,
    "width": 13,
    "height": 34,
    "pivotX": -6,
    "pivotY": -54
  },
  {
    "x": 39,
    "y": 183,
    "width": 13,
    "height": 34,
    "pivotX": -6,
    "pivotY": -53
  },
  {
    "x": 52,
    "y": 183,
    "width": 13,
    "height": 33,
    "pivotX": -6,
    "pivotY": -53
  },
  {
    "x": 65,
    "y": 183,
    "width": 13,
    "height": 33,
    "pivotX": -6,
    "pivotY": -53
  },
  {
    "x": 78,
    "y": 183,
    "width": 13,
    "height": 34,
    "pivotX": -6,
    "pivotY": -54
  },
  {
    "x": 91,
    "y": 183,
    "width": 13,
    "height": 32,
    "pivotX": -6,
    "pivotY": -52
  },
  {
    "x": 0,
    "y": 217,
    "width": 17,
    "height": 31,
    "pivotX": -8,
    "pivotY": -50
  },
  {
    "x": 17,
    "y": 217,
    "width": 19,
    "height": 30,
    "pivotX": -9,
    "pivotY": -50
  },
  {
    "x": 36,
    "y": 217,
    "width": 20,
    "height": 30,
    "pivotX": -9,
    "pivotY": -50
  },
  {
    "x": 56,
    "y": 217,
    "width": 21,
    "height": 30,
    "pivotX": -10,
    "pivotY": -49
  },
  {
    "x": 77,
    "y": 217,
    "width": 21,
    "height": 30,
    "pivotX": -10,
    "pivotY": -49
  },
  {
    "x": 98,
    "y": 217,
    "width": 21,
    "height": 29,
    "pivotX": -10,
    "pivotY": -49
  },
  {
    "x": 119,
    "y": 217,
    "width": 20,
    "height": 30,
    "pivotX": -9,
    "pivotY": -50
  },
  {
    "x": 139,
    "y": 217,
    "width": 19,
    "height": 31,
    "pivotX": -9,
    "pivotY": -50
  }
]