[
  {
    "x": 0,
    "y": 0,
    "width": 16,
    "height": 34,
    "pivotX": -26,
    "pivotY": -53
  },
  {
    "x": 16,
    "y": 0,
    "width": 32,
    "height": 20,
    "pivotX": -36,
    "pivotY": -43
  },
  {
    "x": 48,
    "y": 0,
    "width": 46,
    "height": 9,
    "pivotX": -41,
    "pivotY": -35
  },
  {
    "x": 94,
    "y": 0,
    "width": 51,
    "height": 10,
    "pivotX": -39,
    "pivotY": -39
  },
  {
    "x": 145,
    "y": 0,
    "width": 52,
    "height": 12,
    "pivotX": -37,
    "pivotY": -38
  },
  {
    "x": 197,
    "y": 0,
    "width": 51,
    "height": 10,
    "pivotX": -39,
    "pivotY": -37
  },
  {
    "x": 248,
    "y": 0,
    "width": 46,
    "height": 8,
    "pivotX": -41,
    "pivotY": -35
  },
  {
    "x": 294,
    "y": 0,
    "width": 31,
    "height": 20,
    "pivotX": -35,
    "pivotY": -45
  }
]