[
  {
    "x": 0,
    "y": 0,
    "width": 29,
    "height": 18,
    "pivotX": -32,
    "pivotY": -46
  },
  {
    "x": 29,
    "y": 0,
    "width": 31,
    "height": 14,
    "pivotX": -32,
    "pivotY": -41
  },
  {
    "x": 60,
    "y": 0,
    "width": 29,
    "height": 8,
    "pivotX": -30,
    "pivotY": -35
  },
  {
    "x": 89,
    "y": 0,
    "width": 35,
    "height": 5,
    "pivotX": -26,
    "pivotY": -32
  },
  {
    "x": 124,
    "y": 0,
    "width": 35,
    "height": 7,
    "pivotX": -25,
    "pivotY": -32
  },
  {
    "x": 159,
    "y": 0,
    "width": 35,
    "height": 4,
    "pivotX": -27,
    "pivotY": -32
  },
  {
    "x": 194,
    "y": 0,
    "width": 29,
    "height": 8,
    "pivotX": -30,
    "pivotY": -35
  },
  {
    "x": 223,
    "y": 0,
    "width": 31,
    "height": 14,
    "pivotX": -32,
    "pivotY": -41
  }
]