[
  {
    "x": 0,
    "y": 0,
    "width": 13,
    "height": 23,
    "pivotX": -14,
    "pivotY": -64
  },
  {
    "x": 13,
    "y": 0,
    "width": 10,
    "height": 37,
    "pivotX": -15,
    "pivotY": -83
  },
  {
    "x": 23,
    "y": 0,
    "width": 31,
    "height": 57,
    "pivotX": -22,
    "pivotY": -80
  },
  {
    "x": 54,
    "y": 0,
    "width": 35,
    "height": 41,
    "pivotX": -20,
    "pivotY": -65
  },
  {
    "x": 89,
    "y": 0,
    "width": 33,
    "height": 30,
    "pivotX": -16,
    "pivotY": -53
  },
  {
    "x": 122,
    "y": 0,
    "width": 35,
    "height": 40,
    "pivotX": -20,
    "pivotY": -63
  },
  {
    "x": 157,
    "y": 0,
    "width": 31,
    "height": 57,
    "pivotX": -22,
    "pivotY": -81
  },
  {
    "x": 188,
    "y": 0,
    "width": 10,
    "height": 37,
    "pivotX": -15,
    "pivotY": -85
  }
]